[
    {
        "source": {
            "id": null,
            "name": "GSMArena.com"
        },
        "author": null,
        "title": "OnePlus Nord 2T listed on retailer's website with specs, price, and images - comments - GSMArena.com",
        "description": null,
        "url": "https://www.gsmarena.com/newscomm-54214.php",
        "urlToImage": null,
        "publishedAt": "2022-05-06T06:31:26Z",
        "content": "Just a reheated Nord 2, but hopefully this time with less explosion risk.\r\nThis is worth article? I have confirmed specs for some time:\r\n159.1mm * 73.2mm * 8.2mm * 190g90Hz AMOLED 2400x1080 px 409 pp… [+556 chars]"
    },
    {
        "source": {
            "id": null,
            "name": "India Today"
        },
        "author": null,
        "title": "Garena Free Fire Redeem MAX Codes for May 06, 2022: How to redeem the codes - India Today",
        "description": "Here is all you need to know about the new active codes for the list of New Garena Free Fire Redeem MAX codes and the steps to redeem them.",
        "url": "https://www.indiatoday.in/information/story/garena-free-fire-redeem-max-codes-for-may-06-2022-how-to-redeem-the-codes-1946112-2022-05-06",
        "urlToImage": "https://akm-img-a-in.tosshub.com/indiatoday/images/story/202205/photo-1558993944-ea891dc88d57-647x363.jpeg?PBEqI8rYuZJE.YXi.tJToa.csMi2VpnI",
        "publishedAt": "2022-05-06T06:27:27Z",
        "content": null
    },
    {
        "source": {
            "id": null,
            "name": "LatestLY"
        },
        "author": "Jaspreetsingh Mankoo",
        "title": "Motorola Moto Edge 30 Likely To Debut in India on May 12, 2022 - LatestLY",
        "description": "After launching the Moto Edge 30 smartphone in Europe, the company is gearing up for the Indian launch. Motorola India has teased the device on its official Twitter account.",
        "url": "https://www.latestly.com/technology/motorola-moto-edge-30-likely-to-debut-in-india-on-may-12-2022-3675353.html",
        "urlToImage": "https://st1.latestly.com/wp-content/uploads/2022/04/resize-13-8-784x441.jpg",
        "publishedAt": "2022-05-06T06:17:39Z",
        "content": "After launching the Moto Edge 30 smartphone in Europe, the company is gearing up for the Indian launch. Motorola India has teased the device on its official Twitter account. According to tipster Muku… [+1496 chars]"
    },
    {
        "source": {
            "id": null,
            "name": "Hindustan Times"
        },
        "author": "HT Tech",
        "title": "Quordle 102 answer for May 6, 2022: Check daily Quordle hints and solutions - HT Tech",
        "description": "Quordle 102 answer for May 6, 2022: Today’s Quordle is a double letter extravaganza. It has been a while since Quordle gave us such a difficult word lineup to guess. Don’t hesitate to use these daily Quordle hints, clues and solution",
        "url": "https://tech.hindustantimes.com/tech/news/quordle-102-answer-for-may-6-2022-check-daily-quordle-hints-and-solutions-71651815126892.html",
        "urlToImage": "https://images.hindustantimes.com/tech/img/2022/05/06/1600x900/HT_Tech_(25)_1651471185343_1651815168701.jpg",
        "publishedAt": "2022-05-06T05:35:57Z",
        "content": "Quordle 102 answer for May 6, 2022: Many people think Wordle was the inspiration behind Quordle, like many other spinoffs of the game. However, that isnt the case here. Freddie Meyer decided to make … [+1668 chars]"
    },
    {
        "source": {
            "id": null,
            "name": "News9live.com"
        },
        "author": "News9 Staff",
        "title": "Apple, Google and Microsoft collaborate to expand passwordless sign-in standard by FIDO, W3C - News9 LIVE",
        "description": "This passwordless sign-in standard, already implemented across billions of devices and based on...",
        "url": "https://www.news9live.com/technology/apple-google-and-microsoft-collaborate-to-expand-passwordless-sign-in-standard-by-fido-and-w3c-168622",
        "urlToImage": "https://media.news9live.com/h-upload/2021/11/18/67936-password-1.jpg",
        "publishedAt": "2022-05-06T05:34:43Z",
        "content": "Passwords ideally protect a user's account, but the same is also the Achilles heel when it comes to account security. To enable faster, easier and more secure log-ins without having to remember or re… [+1657 chars]"
    },
    {
        "source": {
            "id": null,
            "name": "Enter21st"
        },
        "author": null,
        "title": "infinix smart 6 first sale today on flipkart at 12pm check price offers and features - Enter21st",
        "description": "New Delhi.Infinix Smart 6 First Sale: A few days ago an entry level phone was launched in India named Infinix Smart 6. The first sale of this phone will be held on Flipkart from 12 noon today. Many offers are also being given with this phone (Infinix Smart 6 …",
        "url": "https://enter21st.com/infinix-smart-6-first-sale-today-on-flipkart-at-12pm-check-price-offers-and-features/",
        "urlToImage": null,
        "publishedAt": "2022-05-06T05:31:12Z",
        "content": "New Delhi.Infinix Smart 6 First Sale: A few days ago an entry level phone was launched in India named Infinix Smart 6. The first sale of this phone will be held on Flipkart from 12 noon today. Many o… [+1479 chars]"
    },
    {
        "source": {
            "id": null,
            "name": "XDA Developers"
        },
        "author": "Mahmoud Itani",
        "title": "WhatsApp Message Reactions are finally rolling out to all users - XDA Developers",
        "description": "After a limited beta test with select users, WhatsApp is now rolling out Message Reactions to all users around the world.",
        "url": "https://www.xda-developers.com/whatsapp-message-reactions-rolling-out/",
        "urlToImage": "https://www.xda-developers.com/files/2022/05/WhatsApp-Message-Reactions.jpg",
        "publishedAt": "2022-05-06T05:00:00Z",
        "content": "WhatsApp is one of the most popular instant messaging (IM) apps out there. Billions of people depend on the Meta-owned service to reach businesses and their loved ones around the world. Despite its p… [+1569 chars]"
    },
    {
        "source": {
            "id": "the-times-of-india",
            "name": "The Times of India"
        },
        "author": "TIMESOFINDIA.COM",
        "title": "Garmin launches Vivomove Sport hybrid smartwatch with OLED display, SpO2, heart rate tracking at Rs 18,99 - Times of India",
        "description": "Garmin India has expanded its hybrid smartwatch lineup with the launch of Vivomove Sport hybrid touchscreen smartwatch.",
        "url": "https://timesofindia.indiatimes.com/gadgets-news/garmin-launches-vivomre-sport-hybrid-smartwatch-with-oled-display-spo2-heart-rate-tracking-at-rs-18990/articleshow/91339414.cms",
        "urlToImage": "https://static.toiimg.com/thumb/msid-91339414,width-1070,height-580,imgsize-569497,resizemode-75,overlay-toi_sw,pt-32,y_pad-40/photo.jpg",
        "publishedAt": "2022-05-06T04:44:00Z",
        "content": null
    },
    {
        "source": {
            "id": null,
            "name": "Www.bgr.in"
        },
        "author": "Shweta Ganjoo",
        "title": "Twitter starts testing chat threads for Spaces: Here’s what it does - BGR India",
        "description": "Twitter has started testing another feature that will bring more ways for Twitter Spaces users to interact with their listeners.",
        "url": "https://www.bgr.in/apps/twitter-starts-testing-chat-threads-for-spaces-heres-what-it-does-1266946/",
        "urlToImage": "https://st1.bgr.in/wp-content/uploads/2022/05/Twitter-Spaces.jpg",
        "publishedAt": "2022-05-06T04:20:30Z",
        "content": "Twitter has been working on a number of new features for enhancing the usability of its platform. We already know that the micro-blogging platform is working on an ‘Edit’ button that will enable user… [+2474 chars]"
    },
    {
        "source": {
            "id": null,
            "name": "News18"
        },
        "author": "Tech Desk",
        "title": "Wordle 321 Answer Today: Wordle Solution For May 6 - News18",
        "description": "Can’t guess the Wordle answer today? If you are finding it difficult to guess the Wordle 320 answer for May 5 then here’s some help.",
        "url": "https://www.news18.com/news/tech/wordle-321-answer-today-wordle-solution-for-may-6-5119237.html",
        "urlToImage": "https://images.news18.com/ibnlive/uploads/2022/03/wordle-2-2-164861085616x9.jpg",
        "publishedAt": "2022-05-06T03:03:12Z",
        "content": "Wordle, the word game has become a viral sensation since its debut. And many have found Wordle to be a good way to test their English language skills. Wordle shares a new word at 12 AM midnight every… [+2923 chars]"
    },
    {
        "source": {
            "id": null,
            "name": "Hindustan Times"
        },
        "author": "Himani Jha",
        "title": "Google Chrome to bring new screenshot tool soon! Check highlights - HT Tech",
        "description": "Google Chrome is testing a new screenshot tool just like the one we already have on Microsoft Edge. Check out all the highlights here.",
        "url": "https://tech.hindustantimes.com/mobile/news/google-chrome-to-bring-new-screenshot-tool-soon-check-highlights-71651802791077.html",
        "urlToImage": "https://images.hindustantimes.com/tech/img/2022/05/06/1600x900/google_chrome_page_1589943632711_1589943633074_1651803006867.jpg",
        "publishedAt": "2022-05-06T02:11:55Z",
        "content": "Google Chrome is reportedly getting a new and advanced screenshot tool just like the one we already have on Microsoft Edge. If you are a Microsoft Edge user, you must be aware of the handy Web Captur… [+1050 chars]"
    },
    {
        "source": {
            "id": null,
            "name": "Hindustan Times"
        },
        "author": "Himani Jha",
        "title": "iPhone tips and tricks: How to recover deleted photos - HT Tech",
        "description": "iPhone comes with a built-in mechanism that doesn’t permanently trash photos when you delete them. Know how you can retrieve the deleted photos.",
        "url": "https://tech.hindustantimes.com/how-to/iphone-tips-and-tricks-how-to-recover-deleted-photos-71651802114175.html",
        "urlToImage": "https://images.hindustantimes.com/tech/img/2022/05/06/1600x900/IMG_3235_1648264890004_1651802297783.jpg",
        "publishedAt": "2022-05-06T01:59:27Z",
        "content": "Smartphones have removed the need for physical albums to save our memories and photos. We keep photos and videos saved on our phone. While its an advantage theres a disadvantage as well. If you delet… [+964 chars]"
    },
    {
        "source": {
            "id": null,
            "name": "YouTube"
        },
        "author": null,
        "title": "Fortnite Playable On iPhone, But The Way You Think | GameSpot News - GameSpot",
        "description": null,
        "url": "https://www.youtube.com/supported_browsers?next_url=https:%2F%2Fwww.youtube.com%2Fwatch%3Fv%3Dlu0GlMmC7LA",
        "urlToImage": null,
        "publishedAt": "2022-05-06T00:00:24Z",
        "content": "Your browser isnt supported anymore. Update it to get the best YouTube experience and our latest features. Learn more\r\nRemind me later"
    },
    {
        "source": {
            "id": null,
            "name": "WindowsLatest"
        },
        "author": null,
        "title": "Microsoft backtracks on Windows 11’s unwanted taskbar changes - WindowsLatest",
        "description": "Windows as a service is constantly developing and evolving, with new features regularly being tested in the preview builds. A Windows 11 preview build recently disabled one of the key taskbar features (drag & drop in flyouts) and a new update is in the proces…",
        "url": "https://www.windowslatest.com/2022/05/06/microsoft-backtracks-on-windows-11s-unwanted-taskbar-changes/",
        "urlToImage": "https://www.windowslatest.com/wp-content/uploads/2022/05/Windows-11-taskbar-change.jpg",
        "publishedAt": "2022-05-05T22:59:17Z",
        "content": "Windows as a service is constantly developing and evolving, with new features regularly being tested in the preview builds. A Windows 11 preview build recently disabled one of the key taskbar feature… [+2134 chars]"
    },
    {
        "source": {
            "id": "google-news",
            "name": "Google News"
        },
        "author": null,
        "title": "Android 12 QPR3 makes finding the Pixel battery widget a breeze - Android Police",
        "description": null,
        "url": "https://news.google.com/__i/rss/rd/articles/CBMiR2h0dHBzOi8vd3d3LmFuZHJvaWRwb2xpY2UuY29tL2FuZHJvaWQtMTItcXByMy1waXhlbC1iYXR0ZXJ5LXdpZGdldC1maXgv0gEA?oc=5",
        "urlToImage": null,
        "publishedAt": "2022-05-05T22:14:00Z",
        "content": null
    },
    {
        "source": {
            "id": "google-news",
            "name": "Google News"
        },
        "author": null,
        "title": "Elden Ring Player Beats Final Bosses in Just Over 30 Seconds - ComicBook.com",
        "description": null,
        "url": "https://news.google.com/__i/rss/rd/articles/CBMiWWh0dHBzOi8vY29taWNib29rLmNvbS9nYW1pbmcvbmV3cy9lbGRlbi1yaW5nLXBsYXllci1iZWF0cy1yYWRhZ29uLWVsZGVuLWJlYXN0LTMwLXNlY29uZHMv0gEA?oc=5",
        "urlToImage": null,
        "publishedAt": "2022-05-05T21:52:00Z",
        "content": null
    },
    {
        "source": {
            "id": null,
            "name": "AnandTech"
        },
        "author": "Gavin Bonshor",
        "title": "AMD Announces Ryzen 5000 C-Series For High-End Chromebooks - AnandTech",
        "description": "In September 2020, AMD released its Ryzen 3000 C-series for Chromebooks, a line up of budget-priced chips based on the 12nm Picasso (Ryzen+) architecture...",
        "url": "https://www.anandtech.com/show/17373/amd-announces-ryzen-5000-cseries-for-highend-chromebooks",
        "urlToImage": "https://images.anandtech.com/doci/17373/AMD%20Ryzen%205000%20C%20Series%20For%20Chromebooks_678x452.jpg",
        "publishedAt": "2022-05-05T21:30:00Z",
        "content": "In September 2020, AMD released its Ryzen 3000 C-series for Chromebooks, a line up of budget-priced chips based on the 12nm Picasso (Ryzen+) architecture that featured up to 4 cores and 8 threads and… [+5590 chars]"
    },
    {
        "source": {
            "id": null,
            "name": "How-To Geek"
        },
        "author": "Mahesh Makvana",
        "title": "How to Turn Off Lens Search in Google Chrome - How-To Geek",
        "description": "Google Chrome makes it easy to disable the Lens search feature and bring back the traditional “Search Google for This Image” context menu option. Here’s how you can do that in Chrome on desktop and Android.",
        "url": "https://www.howtogeek.com/797147/turn-off-google-lens-chrome/",
        "urlToImage": "https://www.howtogeek.com/wp-content/uploads/2020/12/google-chrome-logo-on-a-blue-background.jpg?height=200p&trim=2,2,2,2",
        "publishedAt": "2022-05-05T20:00:57Z",
        "content": "Google Chrome makes it easy to disable the Lens search feature and bring back the traditional “Search Google for This Image” context menu option. Here’s how you can do that in Chrome on desktop and A… [+2129 chars]"
    },
    {
        "source": {
            "id": null,
            "name": "Gadgets Now"
        },
        "author": "Gadgets Now Bureau",
        "title": "New wireless earphones from OnePlus, Realme, Sony and JBL selling under Rs 5,000 in Amazon sale - Gadgets Now",
        "description": "Amazon Summer Sale is live. The 2022 edition of Amazon’s annual sale is offering deals and discounts on a range of products. If you are planning to buy a new pair of earphones, you have quite a few options across brands and budgets. Here we have listed the 20…",
        "url": "https://www.gadgetsnow.com/slideshows/new-wireless-earphones-from-oneplus-realme-sony-and-jbl-selling-under-rs-5000-in-amazon-sale/photolist/91354563.cms",
        "urlToImage": "https://static.toiimg.com/thumb/msid-91354592,width-800,resizemode-4,imgsize-5080/share.jpg",
        "publishedAt": "2022-05-05T18:31:00Z",
        "content": "OnePlus Buds Z2 is the first TWS earbuds from the company to arrive this year. The TWS earbuds come with Active Noise Cancellation up to 40dB. OnePlus Budds Z2 features an 11nn dynamic driver that cl… [+105 chars]"
    },
    {
        "source": {
            "id": "the-verge",
            "name": "The Verge"
        },
        "author": "Allison Johnson",
        "title": "How to set up Back Tap on an iPhone - The Verge",
        "description": "Anyone with an iPhone 8 or newer can set up Back Tap to access an app or function of your choice just by tapping the back of your phone. Here’s how to do it.",
        "url": "https://www.theverge.com/23058569/iphone-back-tap-how-to-ios-14-iphone-8",
        "urlToImage": "https://cdn.vox-cdn.com/thumbor/jtJlixvNM2zkTfs_3Mj-lbDgcxo=/0x146:2040x1214/fit-in/1200x630/cdn.vox-cdn.com/uploads/chorus_asset/file/22863261/akrales_210917_4760_0331.jpg",
        "publishedAt": "2022-05-05T18:16:55Z",
        "content": "All recent iPhones dating back to iPhone 8 can take advantage of the Back Tap feature.\r\nPhoto by Amelia Holowaty Krales / The Verge\r\nBack Tap is one of the easiest ways to put an iPhone function you … [+2860 chars]"
    }
]